LICENSE
MANIFEST.in
README.md
VERSION
requirements_dev.txt
setup.cfg
setup.py
gruut_ipa/__init__.py
gruut_ipa/__main__.py
gruut_ipa/accent.py
gruut_ipa/constants.py
gruut_ipa/espeak.py
gruut_ipa/kirshenbaum.py
gruut_ipa/py.typed
gruut_ipa/sampa.py
gruut_ipa.egg-info/PKG-INFO
gruut_ipa.egg-info/SOURCES.txt
gruut_ipa.egg-info/dependency_links.txt
gruut_ipa.egg-info/entry_points.txt
gruut_ipa.egg-info/requires.txt
gruut_ipa.egg-info/top_level.txt
gruut_ipa/data/phoneme_features.json.gz
gruut_ipa/data/ar/phonemes.txt
gruut_ipa/data/cs-cz/phonemes.txt
gruut_ipa/data/de-de/phonemes.txt
gruut_ipa/data/el-gr/phonemes.txt
gruut_ipa/data/en-gb/phonemes.txt
gruut_ipa/data/en-us/phonemes.txt
gruut_ipa/data/en-us/cmudict/ipa_map.txt
gruut_ipa/data/en-us/cmudict/phonemes.txt
gruut_ipa/data/en-us/espeak/phonemes.txt
gruut_ipa/data/en-us/zamia/ipa_map.txt
gruut_ipa/data/en-us/zamia/phonemes.txt
gruut_ipa/data/es-es/phonemes.txt
gruut_ipa/data/fa/phonemes.txt
gruut_ipa/data/fr-fr/phonemes.txt
gruut_ipa/data/it-it/phonemes.txt
gruut_ipa/data/lb-lb/phonemes.txt
gruut_ipa/data/nl/phonemes.txt
gruut_ipa/data/nl/cgn/ipa_map.txt
gruut_ipa/data/nl/cgn/phonemes.txt
gruut_ipa/data/pt/phonemes.txt
gruut_ipa/data/ru-ru/phonemes.txt
gruut_ipa/data/sv-se/phonemes.txt
gruut_ipa/data/sw/phonemes.txt
gruut_ipa/data/sw/alffa/ipa_map.txt
gruut_ipa/data/sw/alffa/phonemes.txt
gruut_ipa/data/vi-n/phonemes.txt
tests/__init__.py
tests/test_accent.py
tests/test_features.py
tests/test_phone.py
tests/test_phonemes.py
tests/test_pronunciation.py