Metadata-Version: 2.1
Name: gruut-ipa
Version: 0.12.0
Summary: Library for manipulating pronunciations using the International Phonetic Alphabet (IPA)
Home-page: https://github.com/rhasspy/gruut-ipa
Author: Michael Hansen
Author-email: mike@rhasspy.org
License: UNKNOWN
Platform: UNKNOWN
Classifier: Programming Language :: Python :: 3
Classifier: Programming Language :: Python :: 3.6
Classifier: Programming Language :: Python :: 3.7
Classifier: Programming Language :: Python :: 3.8
Classifier: Programming Language :: Python :: 3.9
Classifier: License :: OSI Approved :: MIT License
Requires-Python: >=3.6
